synapsefi
