Metadata-Version: 1.1
Name: synapsefi
Version: 0.0.17
Summary: SynapseFi Python Library
Home-page: https://github.com/SynapseFI/SynapseFi-Python-v2
Author: Synapse Financial Technologies Inc.
Author-email: help@synapsefi.com
License: MIT
Keywords: SynapseFi v3 Rest API
Platform: UNKNOWN
Classifier: Development Status :: 3 - Alpha
Classifier: Intended Audience :: Developers
Classifier: License :: OSI Approved :: MIT License
Classifier: Programming Language :: Python :: 3
